dsyl/__init__.py
dsyl/commonfunctions.py
dsyl-0.5.dist-info/METADATA
dsyl-0.5.dist-info/WHEEL
dsyl-0.5.dist-info/top_level.txt
dsyl-0.5.dist-info/RECORD
