Metadata-Version: 2.1
Name: dsyl
Version: 0.5
Summary: Common Functions
Home-page: UNKNOWN
Author: Yang Lyu
Author-email: smart.lvyang@gmail.com
License: UNKNOWN
Platform: UNKNOWN
